scp_jp/__init__.py
scp_jp/api/__init__.py
scp_jp/api/linker.py
scp_jp/api/member_management.py
scp_jp/audit_logger_client/__init__.py
scp_jp/audit_logger_client/main.py
scp_jp/util/__init__.py
scp_jp/util/fastapi/__init__.py
scp_jp/util/fastapi/cloudflare/__init__.py
scp_jp/util/fastapi/cloudflare/ip_handler.py
scp_jp/wd_idp/__init__.py
scp_jp/wd_idp/main.py
scp_jp_utils-1.2.1.dist-info/licenses/LICENSE
scp_jp_utils-1.2.1.dist-info/METADATA
scp_jp_utils-1.2.1.dist-info/WHEEL
scp_jp_utils-1.2.1.dist-info/top_level.txt
scp_jp_utils-1.2.1.dist-info/RECORD
